{
  "version": "1.0",
  "metadata": {
    "name": "动漫服饰标签库",
    "description": "包含各种动漫角色服装和服饰的标签集合，适用于绘画、AI生成等场景"
  },
  "categories": [
    { "name": "学校制服" },
    { "name": "职业装" },
    { "name": "传统服饰" },
    { "name": "休闲服装" },
    { "name": "特殊服装" },
    { "name": "配饰" },
    { "name": "鞋袜" },
    { "name": "风格" }
  ],
  "tags": [
    { "categoryName": "学校制服", "name": "水手服", "subtitles": ["日式校服", "经典"], "keyword": "sailor_uniform" },
    { "categoryName": "学校制服", "name": "JK制服", "subtitles": ["日本女高中生", "校服"], "keyword": "jk" },
    { "categoryName": "学校制服", "name": "西式校服", "subtitles": ["学院风", "正式"], "keyword": "school_uniform" },
    { "categoryName": "学校制服", "name": "运动服", "subtitles": ["体育服", "校服"], "keyword": "gym_uniform" },
    { "categoryName": "学校制服", "name": "学生制服", "subtitles": ["一般校服", "基本"], "keyword": "student_uniform" },
    
    { "categoryName": "职业装", "name": "女仆装", "subtitles": ["侍女", "服务"], "keyword": "maid" },
    { "categoryName": "职业装", "name": "护士服", "subtitles": ["医护人员", "白大褂"], "keyword": "nurse" },
    { "categoryName": "职业装", "name": "办公室制服", "subtitles": ["OL", "职场"], "keyword": "office_lady" },
    { "categoryName": "职业装", "name": "警察制服", "subtitles": ["执法人员", "制服"], "keyword": "police_uniform" },
    { "categoryName": "职业装", "name": "军装", "subtitles": ["军人", "制服"], "keyword": "military_uniform" },
    { "categoryName": "职业装", "name": "空姐制服", "subtitles": ["航空", "服务"], "keyword": "stewardess" },
    
    { "categoryName": "传统服饰", "name": "和服", "subtitles": ["日本传统", "礼服"], "keyword": "kimono" },
    { "categoryName": "传统服饰", "name": "浴衣", "subtitles": ["夏季和服", "轻便"], "keyword": "yukata" },
    { "categoryName": "传统服饰", "name": "中国旗袍", "subtitles": ["旗袍", "东方"], "keyword": "china_dress" },
    { "categoryName": "传统服饰", "name": "汉服", "subtitles": ["中国传统", "古装"], "keyword": "hanfu" },
    { "categoryName": "传统服饰", "name": "韩服", "subtitles": ["韩国传统", "礼服"], "keyword": "hanbok" },
    
    { "categoryName": "休闲服装", "name": "T恤", "subtitles": ["短袖", "休闲"], "keyword": "t-shirt" },
    { "categoryName": "休闲服装", "name": "衬衫", "subtitles": ["正装", "半正式"], "keyword": "shirt" },
    { "categoryName": "休闲服装", "name": "连帽衫", "subtitles": ["卫衣", "休闲"], "keyword": "hoodie" },
    { "categoryName": "休闲服装", "name": "背心", "subtitles": ["无袖", "层次"], "keyword": "tank_top" },
    { "categoryName": "休闲服装", "name": "短裤", "subtitles": ["夏季", "休闲"], "keyword": "shorts" },
    { "categoryName": "休闲服装", "name": "短裙", "subtitles": ["迷你裙", "女装"], "keyword": "skirt" },
    { "categoryName": "休闲服装", "name": "长裙", "subtitles": ["正式", "女装"], "keyword": "long_skirt" },
    { "categoryName": "休闲服装", "name": "连衣裙", "subtitles": ["裙子", "单件"], "keyword": "dress" },
    { "categoryName": "休闲服装", "name": "牛仔裤", "subtitles": ["休闲", "经典"], "keyword": "jeans" },
    
    { "categoryName": "特殊服装", "name": "泳装", "subtitles": ["比基尼", "海滩"], "keyword": "swimsuit" },
    { "categoryName": "特殊服装", "name": "学校泳装", "subtitles": ["日系", "蓝白"], "keyword": "school_swimsuit" },
    { "categoryName": "特殊服装", "name": "比基尼", "subtitles": ["两件式", "海滩"], "keyword": "bikini" },
    { "categoryName": "特殊服装", "name": "连体泳衣", "subtitles": ["一件式", "游泳"], "keyword": "one-piece_swimsuit" },
    { "categoryName": "特殊服装", "name": "魔法少女装", "subtitles": ["变身", "华丽"], "keyword": "magical_girl" },
    { "categoryName": "特殊服装", "name": "兔女郎", "subtitles": ["Playboy", "耳朵"], "keyword": "bunny_girl" },
    { "categoryName": "特殊服装", "name": "女巫装", "subtitles": ["魔法", "神秘"], "keyword": "witch" },
    { "categoryName": "特殊服装", "name": "哥特装", "subtitles": ["黑暗", "蕾丝"], "keyword": "gothic" },
    
    { "categoryName": "配饰", "name": "眼镜", "subtitles": ["视力矫正", "学术"], "keyword": "glasses" },
    { "categoryName": "配饰", "name": "太阳镜", "subtitles": ["墨镜", "酷炫"], "keyword": "sunglasses" },
    { "categoryName": "配饰", "name": "发饰", "subtitles": ["蝴蝶结", "发夹"], "keyword": "hair_ornament" },
    { "categoryName": "配饰", "name": "发带", "subtitles": ["头巾", "束发"], "keyword": "headband" },
    { "categoryName": "配饰", "name": "帽子", "subtitles": ["头部", "装饰"], "keyword": "hat" },
    { "categoryName": "配饰", "name": "耳环", "subtitles": ["首饰", "耳朵"], "keyword": "earrings" },
    { "categoryName": "配饰", "name": "项链", "subtitles": ["首饰", "颈部"], "keyword": "necklace" },
    { "categoryName": "配饰", "name": "手套", "subtitles": ["保暖", "装饰"], "keyword": "gloves" },
    
    { "categoryName": "鞋袜", "name": "及膝袜", "subtitles": ["长袜", "校服"], "keyword": "knee_highs" },
    { "categoryName": "鞋袜", "name": "过膝袜", "subtitles": ["长袜", "时尚"], "keyword": "thighhighs" },
    { "categoryName": "鞋袜", "name": "短袜", "subtitles": ["袜子", "基本"], "keyword": "socks" },
    { "categoryName": "鞋袜", "name": "裤袜", "subtitles": ["全腿", "紧身"], "keyword": "pantyhose" },
    { "categoryName": "鞋袜", "name": "高跟鞋", "subtitles": ["女鞋", "正式"], "keyword": "high_heels" },
    { "categoryName": "鞋袜", "name": "运动鞋", "subtitles": ["休闲鞋", "舒适"], "keyword": "sneakers" },
    { "categoryName": "鞋袜", "name": "皮鞋", "subtitles": ["正式", "商务"], "keyword": "leather_shoes" },
    { "categoryName": "鞋袜", "name": "靴子", "subtitles": ["长靴", "高帮"], "keyword": "boots" },
    
    { "categoryName": "风格", "name": "洛丽塔", "subtitles": ["蕾丝", "公主"], "keyword": "lolita_fashion" },
    { "categoryName": "风格", "name": "哥特洛丽塔", "subtitles": ["黑色", "蕾丝"], "keyword": "gothic_lolita" },
    { "categoryName": "风格", "name": "甜系洛丽塔", "subtitles": ["甜美", "粉色"], "keyword": "sweet_lolita" },
    { "categoryName": "风格", "name": "朋克", "subtitles": ["叛逆", "金属"], "keyword": "punk" },
    { "categoryName": "风格", "name": "制服诱惑", "subtitles": ["紧身", "性感"], "keyword": "zettai_ryouiki" },
    { "categoryName": "风格", "name": "西部风格", "subtitles": ["牛仔", "乡村"], "keyword": "western" }
  ]
} 